sentinel_to_zarr/__init__.py
sentinel_to_zarr/_version.py
sentinel_to_zarr/napari_sentinel_to_zarr.py
sentinel_to_zarr/sentinel_to_zarr.py
sentinel_to_zarr/_tests/__init__.py
sentinel_to_zarr/_tests/test_sentinel_to_zarr.py
napari_sentinel_to_zarr-0.0.7.dist-info/LICENSE
napari_sentinel_to_zarr-0.0.7.dist-info/METADATA
napari_sentinel_to_zarr-0.0.7.dist-info/WHEEL
napari_sentinel_to_zarr-0.0.7.dist-info/entry_points.txt
napari_sentinel_to_zarr-0.0.7.dist-info/top_level.txt
napari_sentinel_to_zarr-0.0.7.dist-info/RECORD
