Metadata-Version: 2.1
Name: napari-sentinel-to-zarr
Version: 0.0.7
Summary: Writer plugin for napari to save Sentinel tiffs into ome-zarr format
Home-page: https://github.com/DragaDoncila/napari-sentinel-to-zarr
Author: Draga Doncila Pop
Author-email: ddon0001@student.monash.edu
License: MIT
Platform: UNKNOWN
Classifier: Development Status :: 4 - Beta
Classifier: Intended Audience :: Developers
Classifier: Topic :: Software Development :: Testing
Classifier: Programming Language :: Python
Classifier: Programming Language :: Python :: 3
Classifier: Programming Language :: Python :: 3.7
Classifier: Programming Language :: Python :: 3.8
Classifier: Programming Language :: Python :: Implementation :: CPython
Classifier: Programming Language :: Python :: Implementation :: PyPy
Classifier: Operating System :: OS Independent
Classifier: License :: OSI Approved :: MIT License
Requires-Python: >=3.6
Requires-Dist: napari-plugin-engine (>=0.1.4)
Requires-Dist: napari-sentinel-zip
Requires-Dist: ome-zarr
Requires-Dist: numpy
Requires-Dist: toolz (>=0.10)
Requires-Dist: scikit-image
Requires-Dist: numcodecs
Requires-Dist: zarr
Requires-Dist: tqdm
Requires-Dist: dask
Requires-Dist: pandas
Requires-Dist: matplotlib
Requires-Dist: pytest
Requires-Dist: fsspec (>=0.3.3)
